<FORM>
SOLICITAÇÃO       DO  CREDENCIAMENTO          75  – BARES    E RESTAURANTES
CONTRIBUINTE  (RAZÃO SOCIAL)                           INSCRIÇÃO ESTADUAL  CNPJ
ENDEREÇO  (RUA, LOGRADOURO,   ETC.)                NÚMERO      BAIRRO
CIDADE                                             CEP                    TELEFONE
e-mail                                                      Nº DA CNAE PRINCIPAL REGIME DE RECOLHIMENTO
</FORM>
<FORM>
Vem  requerer da Secretaria da Fazenda do Estado de Pernambuco o credenciamento
de redução de base de cálculo para bares, restaurantes e estabelecimentos similares
que trata o Dec. 44.650/2017, Anexo 5, Art. 1º.
Declaramos  que não usufruímos de nenhum  outro benefício e que estamos em
conformidade  com o que preceitua a legislação acima citada.
</FORM>
<SECTION_HEADER>
DOCUMENTAÇÃO NECESSÁRIA
</SECTION_HEADER>
<UNSPECIFIED>
só deverá seguir para a DPC (SEGMENTO DE VAREJO) quando atender totalmente as condições
</UNSPECIFIED>
<UNSPECIFIED>
 ASSINATURA DO SÓCIO OU RESPONSÁVEL (FIRMA RECONHECIDA)                                  LOCAL E DATA
*** O processo                                                                                      do formulário.
</UNSPECIFIED>
<PAGE_BREAK>
