<SECTION_HEADER>
FICHA DE INSCRIÇÃO
</SECTION_HEADER>
<FORM>
Curso: Ciências Sociais         Turma:                 Matrícula: 4470166
CPF:  63562782420                              RG: 43.524.061-4
Responsável  (menores  18 anos): Claudio  Haddad
Endereço  residencial da família do/a Av. Gov. Roberto Silveira, 1900 - Prado, Nova Friburgo, RJ, 28635-000, Brazil
estudante:
Ponto  de Referência:
Endereço  do/a estudante  (caso não
resida com  a família)
Ponto  de referência:
Nº Cel. do/a estudante: +55 98 98112-7250  Nº Cel. Responsável:
</FORM>
<FORM>
Bolsa vinculada ao Projeto de Incentivo à Aprendizagem – PINA
Bolsa de Estudo
Auxílio Alimentação
Auxílio Moradia          Especificar o custo mensal R$
Auxílio Transporte       Especificar o custo diário R$
Auxílio Cópia e Impressão
</FORM>
<PAGE_FOOTER>
Assinatura do/a responsável legal (Menores de 18 anos)
</PAGE_FOOTER>
<UNSPECIFIED>
DepartamentodeEnsino
CoordenaçãoTécnico- Pedagógica
CoordenaçãodePermanênciaeAssistênciaEstudantil
                                       Processo   Seletivo PAAE
 Nome   do/a estudante:  Rafael   Barbastefano
Declaro  para fins de avaliação socioeconômica  que  todas as informações  prestadas ao Serviço Social do
Instituto Federal de Educação,  Ciência e Tecnologia  da  Bahia campus   Barreiras, por meio da  Ficha de
Inscrição e do Formulário  Socioeconômico,   são verídicas e assumo  a responsabilidade pelas declarações
indicadas. Estou ciente que a omissão ou fraude nas informações implicará no desligamento  das bolsas e/ou
auxílios oferecidos pela IFBA. Além  disso, poderei ressarcir os valores obtidos indevidamente e responder
judicialmente, conforme prevê os Códigos Civil e Penal.
                                     11                        ,  05     de 2018            de  2020
      Assinatura do/a  estudante
</UNSPECIFIED>
<PAGE_BREAK>
