<SECTION_HEADER>
Card Holder Information
</SECTION_HEADER>
<SECTION_HEADER>
Card Information
</SECTION_HEADER>
<FORM>
Type of Card:               MasterCard            Visa          Discover          Amex
Card Number:
Expiration Date:                                         3 Digit Code
*Amount   to Charge:
</FORM>
<FORM>
Signature:
                                          (Must have signature to process)
Special Requests:
</FORM>
<UNSPECIFIED>
Credit Card Authorization Form
</UNSPECIFIED>
<PAGE_BREAK>
